src/.DS_Store
src/__init__.py
src/data_pipeline/__init__.py
src/data_pipeline/feature_engineering/__init__.py
src/data_pipeline/feature_engineering/key_smash.py
src/data_pipeline/feature_engineering/word_embedding.py
src/data_pipeline/pre_processing/__init__.py
src/data_pipeline/pre_processing/concatenate_columns.py
src/main.py
src/parser/YAML_parser.py
src/parser/__init__.py
src/parser/const.py
src/parser/feature_engineering_parser.py
src/parser/model_parser.py
src/parser/parser_base.py
src/yamls/basic_example.yaml
gces_dion_package-1.0.0.dist-info/METADATA
gces_dion_package-1.0.0.dist-info/WHEEL
gces_dion_package-1.0.0.dist-info/LICENSE
gces_dion_package-1.0.0.dist-info/RECORD
