Metadata-Version: 2.1
Name: gces-dion-package
Version: 1.0.0
Summary: Pacote do trabalho de GCES.
Author: dionvitor
Author-email: dionvictor11@gmail.com
Requires-Python: >=3.8,<4.0
Classifier: Programming Language :: Python :: 3
Classifier: Programming Language :: Python :: 3.8
Classifier: Programming Language :: Python :: 3.9
Classifier: Programming Language :: Python :: 3.10
Classifier: Programming Language :: Python :: 3.11
